eltools
