Metadata-Version: 2.1
Name: eltools
Version: 1.0.5
Summary: This is a simple package for elegant preprocessing procedure
Home-page: UNKNOWN
Author: Vitalii Balakin
Author-email: balakinvitalyv@gmail.com
License: UNKNOWN
Platform: UNKNOWN
Classifier: Programming Language :: Python :: 3
Classifier: License :: OSI Approved :: MIT License
Classifier: Operating System :: OS Independent
Requires-Python: >=3.6
